llfo/__init__.py
llfo-0.1.0.dist-info/METADATA
llfo-0.1.0.dist-info/WHEEL
llfo-0.1.0.dist-info/RECORD
